README.md
setup.py
gcrssh/__init__.py
gcrssh/main.py
gcrssh.egg-info/PKG-INFO
gcrssh.egg-info/SOURCES.txt
gcrssh.egg-info/dependency_links.txt
gcrssh.egg-info/entry_points.txt
gcrssh.egg-info/top_level.txt