Metadata-Version: 2.1
Name: gcrssh
Version: 0.0.4
Summary: ssh to gcr
Home-page: UNKNOWN
Author: wy
Author-email: 
License: MIT
Platform: UNKNOWN
Classifier: Programming Language :: Python :: 3.5
Classifier: Programming Language :: Python :: 3.6
Classifier: Programming Language :: Python :: 3.7
Classifier: License :: OSI Approved :: MIT License
